{"-AZ5PkpcVatxDCWYGnq_Y":{"audioUrl":"https://storage.googleapis.com/taxi-heringsdorf.firebasestorage.app/callRecordings/2026/05/22/%2B491724659904-0-1779447274291.m4a","createdAt":1779451467541,"customerFound":true,"customerId":"-OjKLKSeiEIiHlG9435L","customerName":"Danilo Mercedes VITO VG LK 111","direction":"incoming","fileSize":641213,"phone":"+491724659904","source":"acr-phone-sync","storagePath":"callRecordings/2026/05/22/+491724659904-0-1779447274291.m4a","timestamp":1779447274291},"-AZ5PkpcXDGqAm0UriF2o":{"audioUrl":"https://storage.googleapis.com/taxi-heringsdorf.firebasestorage.app/callRecordings/2026/05/22/%2B491724659904-1-1779447654479.m4a","createdAt":1779451467543,"customerFound":true,"customerId":"-OjKLKSeiEIiHlG9435L","customerName":"Danilo Mercedes VITO VG LK 111","direction":"outgoing","fileSize":285638,"phone":"+491724659904","source":"acr-phone-sync","storagePath":"callRecordings/2026/05/22/+491724659904-1-1779447654479.m4a","timestamp":1779447654479},"-AZ5PkpcZZUCKzLEG807q":{"audioUrl":"https://storage.googleapis.com/taxi-heringsdorf.firebasestorage.app/callRecordings/2026/05/22/%2B491724659904-1-1779448329780.m4a","createdAt":1779451467545,"customerFound":true,"customerId":"-OjKLKSeiEIiHlG9435L","customerName":"Danilo Mercedes VITO VG LK 111","direction":"outgoing","fileSize":950487,"phone":"+491724659904","source":"acr-phone-sync","storagePath":"callRecordings/2026/05/22/+491724659904-1-1779448329780.m4a","timestamp":1779448329780},"-AZ5PkpcaWvojomEexz09":{"audioUrl":"https://storage.googleapis.com/taxi-heringsdorf.firebasestorage.app/callRecordings/2026/05/22/%2B491703522828-0-1779448635135.m4a","createdAt":1779451467546,"customerFound":true,"customerId":"-OnYViGWZJqPSNzVVCkf","customerName":"Maurice Camp David","direction":"incoming","fileSize":66258,"phone":"+491703522828","source":"acr-phone-sync","storagePath":"callRecordings/2026/05/22/+491703522828-0-1779448635135.m4a","timestamp":1779448635135},"-AZ5Pkpce9kELDDvz_iD9":{"audioUrl":"https://storage.googleapis.com/taxi-heringsdorf.firebasestorage.app/callRecordings/2026/05/22/%2B4915208695144-0-1779449425940.m4a","createdAt":1779451467550,"customerFound":false,"direction":"incoming","fileSize":165451,"phone":"+4915208695144","source":"acr-phone-sync","storagePath":"callRecordings/2026/05/22/+4915208695144-0-1779449425940.m4a","timestamp":1779449425940}}
