{
  "project_info": {
    "project_number": "886448081276",
    "firebase_url": "https://taxi-heringsdorf-default-rtdb.europe-west1.firebasedatabase.app",
    "project_id": "taxi-heringsdorf",
    "storage_bucket": "taxi-heringsdorf.firebasestorage.app"
  },
  "client": [
    {
      "client_info": {
        "mobilesdk_app_id": "1:886448081276:android:154650e0d99b8fce8efcf9",
        "android_client_info": {
          "package_name": "de.taxiheringsdorf.app"
        }
      },
      "oauth_client": [
        {
          "client_id": "886448081276-pu82okhi4b49cgv94sf4js7a8v9qjuvu.apps.googleusercontent.com",
          "client_type": 1,
          "android_info": {
            "package_name": "de.taxiheringsdorf.app",
            "certificate_hash": "361108eafb53a99a8a95c11c20ffaee142c29210"
          }
        },
        {
          "client_id": "886448081276-sl2qbi9fbub9k1g3bhdspb78vqdcacsq.apps.googleusercontent.com",
          "client_type": 1,
          "android_info": {
            "package_name": "de.taxiheringsdorf.app",
            "certificate_hash": "8a92cc444ba40c7fc765ea6dc7fe89729585d8ff"
          }
        },
        {
          "client_id": "886448081276-odgqv3if3hfhrgoesfiavbn8kkn7jkpm.apps.googleusercontent.com",
          "client_type": 3
        }
      ],
      "api_key": [
        {
          "current_key": "AIzaSyAu9CsnLMLLQbXkWckWSV7uIzLB94hJ-HE"
        }
      ],
      "services": {
        "appinvite_service": {
          "other_platform_oauth_client": [
            {
              "client_id": "886448081276-62s2lg4dsqi085v891761tqfg1ngas57.apps.googleusercontent.com",
              "client_type": 3
            }
          ]
        }
      }
    }
  ],
  "configuration_version": "1"
}
